{"createdBy":"ahmerjavedkhan","updatedBy":"ahmarnew","_id":"63ad2e6a21a0d87ea4d05915","projectId":"63f4845e476fc83100e3a899","gitBranchName":"master","name":"Clear BindingKey and Call Bene View API","status":"ACTIVE","services":[{"_id":"63ad739021a0d87ea4d183a3","type":"2","command":{"responseHandler":[],"returns":[],"_id":"63ad739021a0d87ea4d183a4","attributes":{"triggers":[{"createdBy":"ahmerjavedkhan","updatedBy":"ahmerjavedkhan","_id":"63ad2e6221a0d87ea4d057dd","id":"gjfXZTXRcISr16vgPOQpM","name":"Clear View Bene Binding Key","projectId":"62dfaa1ecc4a8a55e4d8a02b","gitBranchName":"Sprint1","services":[{"_id":"63ad2e6221a0d87ea4d057de","type":"11","command":{"responseHandler":[],"returns":[],"_id":"63ad2e6221a0d87ea4d057df","attributes":{"stateName":"accounts","storeType":2,"selectedObjectBindingKey":"selectedObject","dataType":"","sourceBindingKey":""},"type":"4"}}],"createdAt":"29-Dec-2022","updatedAt":"29-Dec-2022","__v":0},{"createdBy":"talib","updatedBy":"muzzamil","_id":"62ea39cbf5f7674f04de0abf","id":"6eeP4-bTakDsclJlwyl_2","projectId":"62dfaa1ecc4a8a55e4d8a02b","gitBranchName":"Sprint1","name":"Get Company Beneficiary","status":"ACTIVE","services":[{"_id":"6336e510c87ebb7734c85c7c","type":"8","command":{"responseHandler":[],"returns":[],"_id":"6336e510c87ebb7734c85c7d","attributes":{"loaderWidgetIds":[906070],"messageWidgetIds":[906070],"responseStateKey":"accounts","responseReturnValue":"data.beneficiary.page","url":"/company-beneficiary/view-beneficiary","checksum":true,"encryption":true,"isDeviceDetails":true,"loginTrigger":false,"formData":false,"logoutTrigger":false,"headers":{"Content-Type":"application/json","Accept":"application/json","channel_key":"001","CSRF_TOKEN":"4c6e939d-db00-4697-82d8-b69bb05aef5a","locale":"en-ltr"},"requestBody":[{"type":4,"name":"Static","key":"pageNumber","value":"1"},{"type":4,"name":"Static","key":"pageSize","value":"5"},{"type":1,"name":"Form","key":"beneficiaryType","value":"category"},{"type":1,"name":"Form","key":"beneficiaryName","value":"beneName"},{"type":1,"name":"Form","key":"employeeId","value":"employeeID"}],"baseURL":"631e018a967b3c4df8e29773","storeType":2},"type":"1"}}],"createdAt":"03-Aug-2022","updatedAt":"30-Sep-2022","__v":11}],"triggerIds":["gjfXZTXRcISr16vgPOQpM","6eeP4-bTakDsclJlwyl_2"]},"type":"1"}}],"id":"expLRh92bI5NwrEzZTnw8","createdAt":"29-Dec-2022","updatedAt":"29-Dec-2022","__v":2}