{"createdBy":"talib","updatedBy":"zeeshan","_id":"62f4d0eded8fa25634cc786b","id":"qF22RhdFgN__2x8kYvy9z","projectId":"63f4845e476fc83100e3a899","gitBranchName":"master","name":"Get Menus","status":"ACTIVE","services":[{"_id":"63356334b4151657381ce9a0","type":"8","command":{"responseHandler":[],"returns":[],"_id":"63356334b4151657381ce9a1","attributes":{"loaderWidgetIds":[906070],"messageWidgetIds":[906070],"responseStateKey":"menusData","responseReturnValue":"data.menus","url":"/menu","checksum":true,"encryption":true,"isDeviceDetails":true,"loginTrigger":false,"formData":false,"logoutTrigger":false,"headers":{"Content-Type":"application/json","Accept":"application/json","channel_key":"001","CSRF_TOKEN":"4c6e939d-db00-4697-82d8-b69bb05aef5a","locale":"en-ltr"},"requestBody":[],"baseURL":"6322eb25967b3c4df8e47be2","storeType":3},"type":"1"}}],"createdAt":"11-Aug-2022","updatedAt":"29-Sep-2022","__v":21}