{
  "id": "FOHJMLxKK_zKDMeOL00pF",
  "name": "Open View Detail Cheque Book Screen",
  "projectId": "63f4845e476fc83100e3a899",
  "gitBranchName": "master",
  "services": [
    {
      "type": "1",
      "command": {
        "type": "3",
        "attributes": {
          "nextWidgetId": "aFPV8_CvC41xu6FWSPxEF",
          "gridRadioValue": "",
          "selectedObjectBindingKey": "selectedObject.payload",
          "editableForm": true
        }
      }
    }
  ],
  "_id": "oHKhLOTeJbM_Lby-FHzLJ",
  "updatedAt": "4/5/2023",
  "createdAt": "4/5/2023",
  "createdBy": "ahmerjavedkhan",
  "updatedBy": "ahmerjavedkhan"
}
