{"createdBy":"muzzamil","updatedBy":"muzzamil","_id":"6319a0c4d005932c10cdb07a","id":"P2QxNKr9Wx1sIqE1181I4","projectId":"63f4845e476fc83100e3a899","gitBranchName":"master","name":"portfolioViewTDR","status":"ACTIVE","services":[{"_id":"6363a55ce2300669e4981b65","type":"8","command":{"responseHandler":[],"returns":[],"_id":"6363a55ce2300669e4981b66","attributes":{"loaderWidgetIds":[906070],"messageWidgetIds":[906070],"responseStateKey":"portfolioViewTdrData","responseReturnValue":"data.portfolios","url":"/portfolio-view/portfolio-view-tdr","checksum":true,"encryption":true,"isDeviceDetails":true,"loginTrigger":false,"formData":false,"logoutTrigger":false,"headers":{"Content-Type":"application/json","Accept":"application/json","channel_key":"001","CSRF_TOKEN":"4c6e939d-db00-4697-82d8-b69bb05aef5a","locale":"en-ltr"},"requestBody":[],"baseURL":"631e018a967b3c4df8e29773","storeType":2},"type":"1"}}],"createdAt":"08-Sep-2022","updatedAt":"03-Nov-2022","__v":5}