{
  "id": "e-Mw5OqX4A63HzPubiQAq",
  "name": "pricing model to document upload for sole properietor",
  "projectId": "63f4845e476fc83100e3a899",
  "gitBranchName": "master",
  "services": [
    {
      "type": "1",
      "command": {
        "type": "2",
        "attributes": {
          "fromWidgetId": "GsHkeyZaiaSjnR8vSVf-W",
          "nextWidgetId": "60-JoICA1uTGOAgECFHt-",
          "gridRadioValue": "Screen",
          "selectedObjectBindingKey": "selectedObject",
          "editableForm": false
        }
      }
    }
  ],
  "_id": "xDmgjEHqVKi3OlFKyQeIa",
  "updatedAt": "4/5/2023",
  "createdAt": "4/5/2023",
  "createdBy": "areeb",
  "updatedBy": "areeb"
}
