{"createdBy":"talha","updatedBy":"talha","_id":"63c8039e582f30545006ae63","id":"PdoQHNhKdopWmljtQ855F","name":"Save collection Array","projectId":"63f4845e476fc83100e3a899","gitBranchName":"master","services":[{"_id":"63c8039e582f30545006ae64","type":"11","command":{"responseHandler":[],"returns":[],"_id":"63c8039e582f30545006ae65","attributes":{"storeType":"","selectedObjectBindingKey":"selectedObject","dataType":"value","destinationBindingKey":"collectionList","sourceBindingKey":"collectionResponse.collections","sourceStoreType":2,"destinationStoreType":2,"targettedType":"value"},"type":"6"}}],"createdAt":"18-Jan-2023","updatedAt":"18-Jan-2023","__v":0}