{
  "id": "GN_WJQ51heiAKHjgUVWEP",
  "name": "set showCusDocUpload true",
  "projectId": "63f4845e476fc83100e3a899",
  "gitBranchName": "master",
  "services": [
    {
      "type": "11",
      "command": {
        "type": "6",
        "attributes": {
          "storeType": "",
          "selectedObjectBindingKey": "selectedObject",
          "dataType": "value",
          "destinationBindingKey": "showCusDocUpload",
          "sourceBindingKey": "form",
          "sourceStoreType": 2,
          "destinationStoreType": 2,
          "logic": { "if": [true, true, true] },
          "changeValueConditonally": true,
          "targettedType": "value"
        }
      }
    }
  ],
  "_id": "jEme6Al9tkqtJs46CsByY",
  "updatedAt": "5/1/2023",
  "createdAt": "5/1/2023",
  "createdBy": "ahmerjavedkhan",
  "updatedBy": "ahmerjavedkhan"
}
